{
  "1": "快递业与邮政",
  "2": "快递、物流",
  "5": "仓储",
  "8": "教育",
  "27": "婴幼儿教育",
  "32": "在线教育",
  "37": "培训机构",
  "39": "出国移民",
  "42": "医疗",
  "43": "就医服务",
  "47": "私立医疗机构",
  "50": "药品信息展示",
  "52": "政务民生",
  "53": "交通违法",
  "55": "博物馆",
  "57": "出入境",
  "59": "邮政",
  "61": "车管所服务",
  "63": "城市道路",
  "65": "高速服务",
  "67": "税务",
  "69": "司法",
  "71": "消防",
  "73": "气象",
  "75": "户政",
  "77": "治安",
  "79": "环保",
  "81": "民政",
  "85": "教育",
  "87": "水电",
  "89": "工商",
  "91": "住建",
  "93": "人力资源",
  "95": "文化",
  "97": "社会保障",
  "99": "金融业",
  "100": "公募基金",
  "102": "信托",
  "104": "网络借贷信息中介（P2P）",
  "106": "保险",
  "108": "银行",
  "110": "出行与交通",
  "111": "打车(网约车)",
  "116": "航空",
  "119": "火车",
  "121": "公交",
  "123": "长途客运",
  "125": "停车",
  "127": "代驾",
  "129": "租车",
  "131": "路况",
  "133": "水运",
  "135": "房地产",
  "138": "物业管理",
  "140": "房地产开发经营",
  "142": "房地产",
  "146": "装修/建材",
  "150": "生活服务",
  "155": "生活缴费",
  "157": "家政",
  "185": "丽人",
  "196": "宠物（非医院类）",
  "198": "环保回收/废品回收",
  "200": "摄影/扩印",
  "202": "婚庆服务",
  "210": "IT科技",
  "211": "硬件与设备",
  "220": "餐饮",
  "221": "点评与推荐",
  "225": "菜谱",
  "231": "旅游",
  "232": "旅游线路",
  "235": "酒店服务",
  "238": "公寓/民宿",
  "240": "门票",
  "242": "出境WiFi",
  "275": "文娱",
  "276": "资讯",
  "279": "视频",
  "281": "语音",
  "283": "音乐",
  "287": "工具",
  "288": "记账",
  "290": "投票",
  "292": "日历",
  "294": "天气",
  "296": "备忘录",
  "298": "办公",
  "300": "字典",
  "302": "图片",
  "304": "商家自营",
  "307": "服装/鞋/箱包",
  "309": "玩具/母婴用品(不含食品)",
  "311": "家电/数码/手机",
  "313": "保健品",
  "315": "珠宝/饰品/眼镜/钟表",
  "317": "运动/户外/乐器",
  "319": "图书报刊/音像/影视/游戏/动漫",
  "321": "食品",
  "323": "鲜花/园艺/工艺品",
  "325": "家居/家饰/家纺",
  "327": "汽车/其他交通工具的配件",
  "329": "办公/文具",
  "331": "五金/建材/化工/矿产品",
  "400": "健康（资讯）服务",
  "401": "股票信息服务平台",
  "402": "商业服务",
  "403": "法律服务",
  "404": "律所",
  "405": "招聘/求职（中介类）",
  "406": "农林牧渔",
  "407": "公益",
  "408": "公益慈善",
  "410": "证券/期货",
  "411": "公立医疗机构",
  "412": "证券/期货投资咨询",
  "413": "软件服务提供商",
  "552": "百货",
  "554": "宠物/农资",
  "556": "邮政",
  "558": "装卸搬运",
  "560": "医疗器械信息展示",
  "562": "医疗器械生产企业",
  "568": "非金融机构自营小额贷款/融资担保/商业保理",
  "578": "教育信息服务",
  "580": "驾校培训",
  "582": "特殊人群教育",
  "590": "出国留学",
  "592": "教育装备",
  "594": "小说",
  "602": "FM/电台",
  "604": "有声读物",
  "606": "动漫",
  "608": "计算类",
  "610": "报价/比价",
  "612": "信息查询",
  "614": "网络代理",
  "616": "效率",
  "618": "健康管理",
  "620": "企业管理",
  "628": "会展服务",
  "630": "基金会",
  "632": "餐饮服务场所/餐饮服务管理企业",
  "634": "餐厅排队",
  "640": "旅游攻略",
  "642": "签证",
  "644": "景区服务",
  "648": "地铁",
  "650": "路桥收费",
  "652": "加油/充电桩",
  "654": "城市交通卡",
  "656": "城市共享交通",
  "658": "高速服务",
  "666": "休闲娱乐",
  "668": "搬家公司",
  "670": "线下超市/便利店",
  "672": "洗浴保健",
  "674": "体育",
  "676": "体育场馆服务",
  "678": "体育赛事",
  "680": "体育培训",
  "682": "在线健身",
  "684": "社交",
  "698": "预约/报名",
  "700": "交警",
  "702": "边防",
  "704": "国安",
  "706": "公证",
  "708": "检察院",
  "710": "法院",
  "712": "纪检审计",
  "714": "财政",
  "716": "公积金",
  "718": "党团组织",
  "720": "安监",
  "722": "医疗",
  "724": "计划生育",
  "726": "体育",
  "728": "水利",
  "730": "食药监",
  "732": "质监",
  "734": "新闻出版及广电",
  "736": "知识产权",
  "738": "旅游局",
  "740": "信访",
  "742": "物价粮食",
  "744": "城管",
  "746": "监狱戒毒",
  "748": "海关",
  "750": "检验检疫",
  "752": "交通",
  "754": "商务",
  "756": "航空",
  "758": "街道居委",
  "760": "农林畜牧海洋",
  "762": "社科档案",
  "764": "政府应急办",
  "766": "科学技术与地质",
  "768": "统计",
  "770": "经济发展与改革",
  "772": "政务服务大厅",
  "774": "广告/设计",
  "776": "公关/推广/市场调查",
  "778": "公证",
  "780": "电商平台",
  "782": "电商平台",
  "784": "海淘",
  "786": "美妆/洗护",
  "788": "机械/电子器件",
  "790": "陌生人交友",
  "792": "熟人交友",
  "794": "社区/论坛",
  "798": "婚恋",
  "800": "问答",
  "802": "新三板信息服务平台",
  "810": "拍卖公司（非文物）",
  "812": "文物拍卖公司",
  "816": "成人用品",
  "818": "酒/盐",
  "864": "互联网医院",
  "866": "宠物医院/兽医",
  "868": "时政信息",
  "870": "典当",
  "872": "笔记",
  "874": "时政信息",
  "876": "会计师事务所",
  "878": "税务师事务所",
  "880": "一般财务服务",
  "882": "汽车",
  "884": "养车/修车",
  "886": "汽车资讯",
  "888": "汽车报价/比价",
  "890": "车展服务",
  "892": "汽车经销商/4S店",
  "894": "汽车厂商",
  "896": "成品油",
  "898": "顺风车(拼车)",
  "900": "纪念币发售",
  "902": "发票查询",
  "904": "征信业务",
  "906": "股票信息服务平台（港股/美股）",
  "908": "药品（非处方药）销售",
  "910": "烟草管理单位",
  "912": "外币兑换",
  "914": "消费金融",
  "916": "图书报刊/音像/影视/游戏/动漫等出版物",
  "918": "医疗-血液、干细胞服务",
  "922": "点餐平台",
  "924": "外卖平台",
  "926": "汽车内饰/外饰",
  "930": "专利/商标代理",
  "932": "亲子/司法鉴定",
  "939": "游戏",
  "941": "休闲游戏",
  "953": "动作游戏",
  "969": "棋牌游戏",
  "975": "竞技游戏",
  "985": "角色游戏",
  "997": "其他游戏",
  "1005": "公共印章刻制",
  "1007": "第三方人力资源服务",
  "1011": "直播",
  "1013": "开锁服务",
  "1015": "实物黄金买卖",
  "1017": "初级食用农产品",
  "1019": "社交红包",
  "1021": "社交红包",
  "1023": "直播答题",
  "1025": "宗教信息服务",
  "1031": "电话卡销售",
  "1033": "寄件/收件",
  "1035": "文化互动",
  "1039": "营业性演出票务",
  "1041": "其他医学健康服务",
  "1043": "在线视频课程",
  "1045": "汽车预售服务",
  "1047": "视频客服",
  "1049": "医疗器械自营",
  "1051": "医疗器械经营销售平台",
  "1055": "预付卡销售",
  "1067": "快递柜",
  "1069": "旅游退税",
  "1071": "基础电信运营商",
  "1073": "电信业务代理商",
  "1077": "信用卡",
  "1079": "多方通信",
  "1081": "司法拍卖",
  "1083": "临床试验",
  "1085": "货物运输",
  "1087": "学历教育（学校）",
  "1089": "素质教育",
  "1091": "教育平台",
  "1093": "学术期刊",
  "1095": "出租车",
  "1097": "第三方互联网保险",
  "1099": "私募基金",
  "1101": "网信系统",
  "1107": "健康数据统计",
  "1113": "电子汇票"
}